fxiaoke/AccountObj.py
fxiaoke/__init__.py
fxiaoke/api.py
fxiaoke/baseObj.py
fxiaoke/crmLog_query.py
fxiaoke/op_create.py
fxiaoke/op_get.py
fxiaoke/op_query.py
fxiaoke/session.py
fxiaoke_python-0.0.3.dist-info/LICENSE
fxiaoke_python-0.0.3.dist-info/METADATA
fxiaoke_python-0.0.3.dist-info/WHEEL
fxiaoke_python-0.0.3.dist-info/top_level.txt
fxiaoke_python-0.0.3.dist-info/RECORD
