Metadata-Version: 2.1
Name: fxiaoke-python
Version: 0.0.3
Summary: fxiaoke CRM(ShareCRM) api.
Home-page: https://github.com/wbchn/fxiaoke-python
Author: wbin
Author-email: wbin.chn@gmail.com
License: Apache License 2.0
Platform: UNKNOWN
Requires-Python: ~=3.8
Requires-Dist: requests (>=2.26.0)
